KratosMultiphysics/.libs/KratosPfemFluidDynamicsApplication.pyd
KratosMultiphysics/.libs/KratosPfemFluidDynamicsCore.dll
KratosMultiphysics/.libs/KratosPfemFluidDynamicsCore.lib
KratosMultiphysics/PfemFluidDynamicsApplication/__init__.py
KratosMultiphysics/PfemFluidDynamicsApplication/assign_eulerian_inlet_process.py
KratosMultiphysics/PfemFluidDynamicsApplication/assign_lagrangian_inlet_process.py
KratosMultiphysics/PfemFluidDynamicsApplication/assign_modulus_and_direction_to_conditions_process.py
KratosMultiphysics/PfemFluidDynamicsApplication/assign_modulus_and_direction_to_nodes_process.py
KratosMultiphysics/PfemFluidDynamicsApplication/assign_scalar_to_nodes_process.py
KratosMultiphysics/PfemFluidDynamicsApplication/assign_vector_components_to_nodes_process.py
KratosMultiphysics/PfemFluidDynamicsApplication/cut_pfem_fluid_complete_mesher.py
KratosMultiphysics/PfemFluidDynamicsApplication/fluid_mesher.py
KratosMultiphysics/PfemFluidDynamicsApplication/fluid_meshing_domain.py
KratosMultiphysics/PfemFluidDynamicsApplication/fluid_meshing_strategy.py
KratosMultiphysics/PfemFluidDynamicsApplication/lagrangian_rotation_process.py
KratosMultiphysics/PfemFluidDynamicsApplication/pfem_check_and_prepare_fluid_model_process.py
KratosMultiphysics/PfemFluidDynamicsApplication/pfem_dem_solver.py
KratosMultiphysics/PfemFluidDynamicsApplication/pfem_fluid_complete_mesher.py
KratosMultiphysics/PfemFluidDynamicsApplication/pfem_fluid_dynamics_analysis.py
KratosMultiphysics/PfemFluidDynamicsApplication/pfem_fluid_gid_output_process.py
KratosMultiphysics/PfemFluidDynamicsApplication/pfem_fluid_keeping_nodes_mesher.py
KratosMultiphysics/PfemFluidDynamicsApplication/pfem_fluid_nodal_integration_solver.py
KratosMultiphysics/PfemFluidDynamicsApplication/pfem_fluid_none_mesher.py
KratosMultiphysics/PfemFluidDynamicsApplication/pfem_fluid_solver.py
KratosMultiphysics/PfemFluidDynamicsApplication/pfem_fluid_thermal_solver.py
KratosPfemFluidDynamicsApplication-10.2.3.dist-info/METADATA
KratosPfemFluidDynamicsApplication-10.2.3.dist-info/WHEEL
KratosPfemFluidDynamicsApplication-10.2.3.dist-info/top_level.txt
KratosPfemFluidDynamicsApplication-10.2.3.dist-info/RECORD
